{
  "updated": "2026-04-21",
  "note": "Edit this file to add or update events. Categories: announcement, government, budget, schools, hearing, community, health. Date format: YYYY-MM-DD.",
  "events": [
    {
      "id": 1,
      "date": "2026-04-10",
      "title": "📢 FY2026-27 Budget Public Input Period Open",
      "time": "Ongoing — public hearing May 26 at 7 PM",
      "location": "Submit online at dconc.gov or in writing to the Board of Commissioners",
      "category": "announcement",
      "links": [
        { "label": "Submit Comment", "url": "https://www.dconc.gov/Board-of-Commissioners/Meetings-and-Announcements/Rules-for-Citizens-and-Public-Comment" },
        { "label": "Budget Docs", "url": "https://www.dconc.gov/Budget-and-Management-Services" }
      ]
    },
    {
      "id": 2,
      "date": "2026-04-12",
      "title": "📢 Durham County Seeks Applicants for Housing Advisory Board",
      "time": "Applications due May 1, 2026",
      "location": "Apply online at dconc.gov",
      "category": "announcement",
      "links": [
        { "label": "Apply Now", "url": "https://www.dconc.gov/Board-of-Commissioners/Boards-and-Commissions" }
      ]
    },
    {
      "id": 3,
      "date": "2026-04-14",
      "title": "Board of Commissioners – Regular Meeting",
      "time": "Monday · 9:00 AM",
      "location": "200 E. Main St., Durham – Room 2A",
      "category": "government",
      "links": [
        { "label": "Agenda", "url": "https://www.dconc.gov/Board-of-Commissioners/Meetings-and-Announcements/BOCC-Agendas-and-Video-Library" },
        { "label": "Live Stream", "url": "https://www.youtube.com/user/DCoWebmaster/videos" },
        { "label": "Public Comment", "url": "https://www.dconc.gov/Board-of-Commissioners/Meetings-and-Announcements/Rules-for-Citizens-and-Public-Comment" }
      ]
    },
    {
      "id": 4,
      "date": "2026-04-17",
      "title": "Durham Public Schools Board of Education",
      "time": "Thursday · 5:30 PM",
      "location": "511 Cleveland St., Durham",
      "category": "schools",
      "links": [
        { "label": "Agenda", "url": "https://www.dpsnc.net/domain/133" },
        { "label": "Watch Online", "url": "https://www.dpsnc.net" }
      ]
    },
    {
      "id": 5,
      "date": "2026-04-23",
      "title": "City-County Planning Commission",
      "time": "Wednesday · 5:00 PM",
      "location": "Durham City Hall, 101 City Hall Plaza",
      "category": "government",
      "links": [
        { "label": "Agenda", "url": "https://www.durhamnc.gov/579/Planning-Commission" }
      ]
    },
    {
      "id": 6,
      "date": "2026-04-27",
      "title": "Board of Commissioners – Regular Meeting",
      "time": "Monday · 9:00 AM",
      "location": "200 E. Main St., Durham – Room 2A",
      "category": "government",
      "links": [
        { "label": "Agenda", "url": "https://www.dconc.gov/Board-of-Commissioners/Meetings-and-Announcements/BOCC-Agendas-and-Video-Library" },
        { "label": "Live Stream", "url": "https://www.youtube.com/user/DCoWebmaster/videos" },
        { "label": "Public Comment", "url": "https://www.dconc.gov/Board-of-Commissioners/Meetings-and-Announcements/Rules-for-Citizens-and-Public-Comment" }
      ]
    },
    {
      "id": 7,
      "date": "2026-04-25",
      "title": "Durham Farmers Market – Season Opener",
      "time": "Saturday · 8:00 AM – 12:00 PM",
      "location": "501 Foster St., Durham (American Tobacco Campus)",
      "category": "community",
      "links": [
        { "label": "Details", "url": "https://www.durhamfarmersmarket.com" }
      ]
    },
    {
      "id": 8,
      "date": "2026-05-01",
      "title": "📢 Durham County Housing Advisory Board Applications Due",
      "time": "Deadline: May 1, 2026",
      "location": "Apply online at dconc.gov",
      "category": "announcement",
      "links": [
        { "label": "Apply", "url": "https://www.dconc.gov/Board-of-Commissioners/Boards-and-Commissions" }
      ]
    },
    {
      "id": 9,
      "date": "2026-05-05",
      "title": "Durham County Mental Health Advisory Board",
      "time": "Tuesday · 4:00 PM",
      "location": "414 E. Main St., Durham",
      "category": "health",
      "links": [
        { "label": "Details", "url": "https://www.dconc.gov" }
      ]
    },
    {
      "id": 10,
      "date": "2026-05-11",
      "title": "County Manager Presents FY2026-27 Recommended Budget",
      "time": "Monday · 7:00 PM",
      "location": "200 E. Main St., Durham – Commissioners Chambers",
      "category": "budget",
      "links": [
        { "label": "Live Stream", "url": "https://www.youtube.com/user/DCoWebmaster/videos" },
        { "label": "Budget Docs", "url": "https://www.dconc.gov/Budget-and-Management-Services" }
      ]
    },
    {
      "id": 11,
      "date": "2026-05-12",
      "title": "Board of Commissioners – Regular Meeting",
      "time": "Tuesday · 9:00 AM",
      "location": "200 E. Main St., Durham – Room 2A",
      "category": "government",
      "links": [
        { "label": "Agenda", "url": "https://www.dconc.gov/Board-of-Commissioners/Meetings-and-Announcements/BOCC-Agendas-and-Video-Library" },
        { "label": "Live Stream", "url": "https://www.youtube.com/user/DCoWebmaster/videos" }
      ]
    },
    {
      "id": 12,
      "date": "2026-05-14",
      "title": "Durham Public Schools Board of Education",
      "time": "Thursday · 5:30 PM",
      "location": "511 Cleveland St., Durham",
      "category": "schools",
      "links": [
        { "label": "Agenda", "url": "https://www.dpsnc.net/domain/133" }
      ]
    },
    {
      "id": 13,
      "date": "2026-05-19",
      "title": "BOCC Budget Work Session (FY2026-27)",
      "time": "Monday · 9:00 AM",
      "location": "200 E. Main St., Durham",
      "category": "budget",
      "links": [
        { "label": "Live Stream", "url": "https://www.youtube.com/user/DCoWebmaster/videos" }
      ]
    },
    {
      "id": 14,
      "date": "2026-05-21",
      "title": "BOCC Budget Work Session (FY2026-27)",
      "time": "Thursday · 1:00 PM",
      "location": "200 E. Main St., Durham",
      "category": "budget",
      "links": [
        { "label": "Live Stream", "url": "https://www.youtube.com/user/DCoWebmaster/videos" }
      ]
    },
    {
      "id": 15,
      "date": "2026-05-23",
      "title": "Durham Earth Day Community Festival",
      "time": "Saturday · 10:00 AM – 4:00 PM",
      "location": "Durham Central Park, 501 Foster St.",
      "category": "community",
      "links": [
        { "label": "Details", "url": "https://www.durhamcentralpark.org" }
      ]
    },
    {
      "id": 16,
      "date": "2026-05-26",
      "title": "Public Hearing: FY2026-27 Budget",
      "time": "Tuesday · 7:00 PM",
      "location": "200 E. Main St., Durham – Commissioners Chambers",
      "category": "hearing",
      "links": [
        { "label": "Sign Up to Speak", "url": "https://www.dconc.gov/Board-of-Commissioners/Meetings-and-Announcements/Rules-for-Citizens-and-Public-Comment" },
        { "label": "Live Stream", "url": "https://www.youtube.com/user/DCoWebmaster/videos" }
      ]
    },
    {
      "id": 17,
      "date": "2026-05-28",
      "title": "BOCC Budget Work Session (FY2026-27)",
      "time": "Thursday · 9:00 AM",
      "location": "200 E. Main St., Durham",
      "category": "budget",
      "links": [
        { "label": "Live Stream", "url": "https://www.youtube.com/user/DCoWebmaster/videos" }
      ]
    },
    {
      "id": 18,
      "date": "2026-06-02",
      "title": "BOCC Budget Work Session (FY2026-27)",
      "time": "Tuesday · 9:00 AM",
      "location": "200 E. Main St., Durham",
      "category": "budget",
      "links": [
        { "label": "Live Stream", "url": "https://www.youtube.com/user/DCoWebmaster/videos" }
      ]
    },
    {
      "id": 19,
      "date": "2026-06-04",
      "title": "BOCC Budget Work Session (FY2026-27)",
      "time": "Thursday · 1:00 PM",
      "location": "200 E. Main St., Durham",
      "category": "budget",
      "links": [
        { "label": "Live Stream", "url": "https://www.youtube.com/user/DCoWebmaster/videos" }
      ]
    },
    {
      "id": 20,
      "date": "2026-06-08",
      "title": "Board of Commissioners – FY2026-27 Budget Adoption Vote",
      "time": "Monday · 7:00 PM",
      "location": "200 E. Main St., Durham – Commissioners Chambers",
      "category": "budget",
      "links": [
        { "label": "Agenda", "url": "https://www.dconc.gov/Board-of-Commissioners/Meetings-and-Announcements/BOCC-Agendas-and-Video-Library" },
        { "label": "Live Stream", "url": "https://www.youtube.com/user/DCoWebmaster/videos" },
        { "label": "Public Comment", "url": "https://www.dconc.gov/Board-of-Commissioners/Meetings-and-Announcements/Rules-for-Citizens-and-Public-Comment" }
      ]
    },
    {
      "id": 21,
      "date": "2026-06-09",
      "title": "Durham County Health Dept. — Free Vaccination Clinic",
      "time": "Tuesday · 10:00 AM – 2:00 PM",
      "location": "Durham County Human Services, 414 E. Main St.",
      "category": "health",
      "links": [
        { "label": "Details", "url": "https://www.dconc.gov/Public-Health/Clinical-Services" }
      ]
    }
  ]
}
